coati_payroll/__init__.py
coati_payroll/app.py
coati_payroll/audit_helpers.py
coati_payroll/auth.py
coati_payroll/cli.py
coati_payroll/config.py
coati_payroll/demo_data.py
coati_payroll/enums.py
coati_payroll/forms.py
coati_payroll/formula_engine_examples.py
coati_payroll/i18n.py
coati_payroll/initial_data.py
coati_payroll/interes_engine.py
coati_payroll/locale_config.py
coati_payroll/log.py
coati_payroll/model.py
coati_payroll/plugin_manager.py
coati_payroll/rate_limiting.py
coati_payroll/rbac.py
coati_payroll/report_engine.py
coati_payroll/report_export.py
coati_payroll/schema_validator.py
coati_payroll/security.py
coati_payroll/system_reports.py
coati_payroll/vacation_service.py
coati_payroll/version.py
coati_payroll/formula_engine/__init__.py
coati_payroll/formula_engine/data_sources.py
coati_payroll/formula_engine/engine.py
coati_payroll/formula_engine/exceptions.py
coati_payroll/formula_engine/novelty_codes.py
coati_payroll/formula_engine/ast/__init__.py
coati_payroll/formula_engine/ast/ast_visitor.py
coati_payroll/formula_engine/ast/expression_evaluator.py
coati_payroll/formula_engine/ast/safe_operators.py
coati_payroll/formula_engine/ast/type_converter.py
coati_payroll/formula_engine/execution/__init__.py
coati_payroll/formula_engine/execution/execution_context.py
coati_payroll/formula_engine/execution/step_executor.py
coati_payroll/formula_engine/execution/variable_store.py
coati_payroll/formula_engine/results/__init__.py
coati_payroll/formula_engine/results/execution_result.py
coati_payroll/formula_engine/steps/__init__.py
coati_payroll/formula_engine/steps/assignment_step.py
coati_payroll/formula_engine/steps/base_step.py
coati_payroll/formula_engine/steps/calculation_step.py
coati_payroll/formula_engine/steps/conditional_step.py
coati_payroll/formula_engine/steps/step_factory.py
coati_payroll/formula_engine/steps/tax_lookup_step.py
coati_payroll/formula_engine/tables/__init__.py
coati_payroll/formula_engine/tables/bracket_calculator.py
coati_payroll-0.0.12.dist-info/LICENSE
coati_payroll-0.0.12.dist-info/METADATA
coati_payroll-0.0.12.dist-info/WHEEL
coati_payroll-0.0.12.dist-info/entry_points.txt
coati_payroll-0.0.12.dist-info/top_level.txt
coati_payroll-0.0.12.dist-info/RECORD
