Metadata-Version: 2.1
Name: coati-payroll
Version: 0.0.12
Summary: A jurisdiction-agnostic payroll calculation engine.
Requires-Python: >=3.11
License-File: LICENSE
Requires-Dist: alembic==1.18.1
Requires-Dist: argon2-cffi
Requires-Dist: babel
Requires-Dist: configobj
Requires-Dist: cryptography
Requires-Dist: dramatiq[redis]
Requires-Dist: email-validator
Requires-Dist: flask
Requires-Dist: flask-alembic==3.2.0
Requires-Dist: flask-babel
Requires-Dist: flask-caching
Requires-Dist: flask-limiter
Requires-Dist: flask-login
Requires-Dist: flask-mail
Requires-Dist: flask-reuploaded
Requires-Dist: flask-session
Requires-Dist: flask-sqlalchemy
Requires-Dist: flask-weasyprint
Requires-Dist: flask-wtf
Requires-Dist: huey
Requires-Dist: mysql-connector-python
Requires-Dist: openpyxl
Requires-Dist: orjson
Requires-Dist: pg8000
Requires-Dist: python-dateutil
Requires-Dist: python-ulid
Requires-Dist: sqlalchemy
Requires-Dist: redis
Requires-Dist: waitress
Requires-Dist: weasyprint
Requires-Dist: wtforms
